silentcipher/__init__.py
silentcipher/model.py
silentcipher/server.py
silentcipher/stft.py
silentcipher-1.0.5.dist-info/LICENSE
silentcipher-1.0.5.dist-info/METADATA
silentcipher-1.0.5.dist-info/WHEEL
silentcipher-1.0.5.dist-info/top_level.txt
silentcipher-1.0.5.dist-info/RECORD
