Metadata-Version: 2.1
Name: silentcipher
Version: 1.0.5
Summary: Artefact free robust high quality audio watermarking
Author-email: Mayank Kumar Singh <mayank.a.singh@sony.com>
Project-URL: Homepage, https://github.com/sony/silentcipher
Project-URL: Issues, https://github.com/sony/silentcipher/issues
Classifier: Programming Language :: Python :: 3
Classifier: License :: OSI Approved :: MIT License
Classifier: Operating System :: OS Independent
Requires-Python: >=3.8
License-File: LICENSE
Requires-Dist: librosa >=0.9.0rc0
Requires-Dist: torch <=2.0.0,>=1.8.0
Requires-Dist: numpy >=1.25.2
Requires-Dist: soundfile >=0.12.1
Requires-Dist: scipy >=1.11.4
Requires-Dist: pyaml >=24.4.0
Requires-Dist: Flask >=2.2.5
Requires-Dist: pydub >=0.25.1
Requires-Dist: huggingface-hub >=0.23.4
